wxtwitterbot/__init__.py
wxtwitterbot/const.py
wxtwitterbot/envvarname.py
wxtwitterbot/main.py
wxtwitterbot/twitter.py
wxtwitterbot/util.py
wxtwitterbot/tasks/__init__.py
wxtwitterbot/tasks/airquality.py
wxtwitterbot/tasks/lunartime.py
wxtwitterbot/tasks/solartime.py
wxtwitterbot-1.3.2.dist-info/LICENSE
wxtwitterbot-1.3.2.dist-info/METADATA
wxtwitterbot-1.3.2.dist-info/WHEEL
wxtwitterbot-1.3.2.dist-info/top_level.txt
wxtwitterbot-1.3.2.dist-info/RECORD
