Metadata-Version: 2.1
Name: wxtwitterbot
Version: 1.3.2
Summary: Wx Twitter Bot
Home-page: https://github.com/karjanme/wx-twitter-bot
Author: Karl Jansen
Author-email: jnsnkrl@live.com
License: MIT
Classifier: Development Status :: 5 - Production/Stable
Classifier: Intended Audience :: Developers
Classifier: Programming Language :: Python :: 3
Classifier: License :: OSI Approved :: MIT License
Classifier: Operating System :: OS Independent
Requires-Python: >=3.8
License-File: LICENSE
Requires-Dist: airnowpy
Requires-Dist: astral
Requires-Dist: pylunar
Requires-Dist: python-dotenv
Requires-Dist: pytz
Requires-Dist: tweepy
Requires-Dist: requests
